akshay_jay/__init__.py
akshay_jay/example.py
akshay_jay/visualization.py
akshay_jay-0.0.2.dist-info/LICENSE
akshay_jay-0.0.2.dist-info/METADATA
akshay_jay-0.0.2.dist-info/WHEEL
akshay_jay-0.0.2.dist-info/top_level.txt
akshay_jay-0.0.2.dist-info/RECORD
