Metadata-Version: 2.1
Name: akshay-jay
Version: 0.0.2
Summary: A small example package
Author-email: akshayj <author@example.com>
Project-URL: Homepage, https://github.com/pypa/sampleproject
Classifier: Natural Language :: English
Classifier: Programming Language :: Python :: 3
Classifier: Programming Language :: Python :: 3.4
Classifier: Programming Language :: Python :: 3.5
Classifier: Programming Language :: Python :: 3.6
Classifier: License :: OSI Approved :: MIT License
Requires-Python: >=3
License-File: LICENSE
